fastmcp_agents/library/agents/__init__.py
fastmcp_agents/library/agents/elasticsearch/agents.py
fastmcp_agents/library/agents/elasticsearch/models.py
fastmcp_agents/library/agents/elasticsearch/prompts.py
fastmcp_agents/library/agents/elasticsearch/server.py
fastmcp_agents/library/agents/filesystem/__init__.py
fastmcp_agents/library/agents/filesystem/agents.py
fastmcp_agents/library/agents/filesystem/prompts.py
fastmcp_agents/library/agents/filesystem/server.py
fastmcp_agents/library/agents/github/__init__.py
fastmcp_agents/library/agents/github/agents.py
fastmcp_agents/library/agents/github/models.py
fastmcp_agents/library/agents/github/prompts.py
fastmcp_agents/library/agents/github/server.py
fastmcp_agents/library/agents/shared/logging.py
fastmcp_agents/library/agents/shared/models.py
fastmcp_agents/library/agents/simple_code/__init__.py
fastmcp_agents/library/agents/simple_code/agents.py
fastmcp_agents/library/agents/simple_code/models.py
fastmcp_agents/library/agents/simple_code/prompts.py
fastmcp_agents/library/agents/simple_code/server.py
fastmcp_agents_library_agents-0.5.10.dist-info/WHEEL
fastmcp_agents_library_agents-0.5.10.dist-info/entry_points.txt
fastmcp_agents_library_agents-0.5.10.dist-info/METADATA
fastmcp_agents_library_agents-0.5.10.dist-info/RECORD
