Metadata-Version: 2.3
Name: fastmcp-agents-library-agents
Version: 0.5.10
Summary: Agents with no dependencies on other libraries
Author: William Easton
Author-email: William Easton <williamseaston@gmail.com>
Requires-Dist: fastmcp-agents-library-mcp
Requires-Dist: fastmcp-agents-bridge-pydantic-ai>=0.1.2
Requires-Dist: gitpython>=3.1.44
Requires-Dist: pydantic-ai
Requires-Python: >=3.13
